Topsis/__init__.py
Topsis/topsis.py
Topsis_Sarika_102203880-1.0.1.dist-info/METADATA
Topsis_Sarika_102203880-1.0.1.dist-info/WHEEL
Topsis_Sarika_102203880-1.0.1.dist-info/top_level.txt
Topsis_Sarika_102203880-1.0.1.dist-info/RECORD
