Metadata-Version: 2.2
Name: Topsis-Sarika-102203880
Version: 1.0.1
Summary: A Python package for TOPSIS decision making.
Home-page: https://github.com/Sarikaa9/Topsis-Sarika-102203880.git
Author: Sarika
Author-email: sarika090903@gmail.com
Requires-Dist: numpy
Requires-Dist: pandas
Dynamic: author
Dynamic: author-email
Dynamic: description
Dynamic: description-content-type
Dynamic: home-page
Dynamic: requires-dist
Dynamic: summary
